<item>
  <title>L experience interdite (2017) torrent VF</title>
  <thumbnail>https://images-na.ssl-images-amazon.com/images/M/MV5BMTExMTk2ODk0NDNeQTJeQWpwZ15BbWU4MDMxNTExNjIy._V1_UX182_CR0,0,182,268_AL_.jpg</thumbnail>
  <multilink>
    <link>plugin://plugin.video.quasar/play?uri=magnet:?xt=urn:btih:a214202fa9419e57431294096183a992bacf44e4&dn=Flatiners.2017.720p&tr=udp://tracker.coppersurfer.tk:6969&tr=udp://coppersurfer.tk:6969/announce&tr=udp://tracker4.piratux.com:6969/announce&tr=udp://eddie4.nl:6969/announce&tr=udp://tracker.opentrackr.org:1337/announce&tr=udp://tracker.coppersurfer.tk:80&tr=udp://tracker.openbittorrent.com:80/announce&tr=udp://open.demonii.com:1337/announce&tr=udp://tracker.pomf.se&tr=udp://tracker.blackunicorn.xyz:6969&tr=udp://tracker.leechers-paradise.org:6969&tr=http://retracker.uln-ix.ru/announce&tr=http://tracker1.infohash.org/announce&tr=udp://p4p.arenabg.ch:1337&tr=udp://p4p.arenabg.com:1337&tr=udp://glotorrents.pw:6969/announce&tr=http://tracker.nwps.ws:6969/announce&tr=http://tracker.dler.org:6969/announce&tr=http://tracker.flashtorrents.org:6969/announce&tr=http://mgtracker.org:2710/announce&tr=http://retracker.adminko.org/announce&tr=http://torrent.fedoraproject.org:6969/announce&tr=http://tracker.best-torrents.net:6969/announce&tr=http://tracker.tfile.me/announce&tr=udp://exodus.desync.com:6969&tr=udp://torrent.gresille.org:80/announce&tr=http://tracker.aletorrenty.pl:2710/announce&tr=http://tracker.pubt.net:2710/announce&tr=http://exodus.desync.com/announce&tr=udp://tracker.publichd.eu:80/announce&tr=http://inferno.demonoid.ph:3389/announce&tr=udp://tracker.publicbt.com:80/announce&tr=http://tracker.ex.ua/announce&tr=udp://exodus.desync.com:6969&tr=http://exodus.desync.com/announce&tr=udp://tracker.istole.it:80/announce&tr=udp://tracker.1337x.org:80/announce&tr=http://fr33dom.h33t.com:3310/announce&tr=udp://tracker.1337x.org:80/announce&tr=http://tracker.torrentbay.to:6969/announce&tr=udp://tracker.publichd.eu:80/announce&tr=http://tracker.trackerfix.com/announce&tr=udp://tracker.ccc.de:80/announce&tr=udp://pow7.com:80/announce&tr=udp://tracker.token.ro:80/announce&tr=udp://ipv4.tracker.harry.lu:80/announce&tr=http://bt.rghost.net/announce&tr=http://cpleft.com:2710/announce&tr=udp://9.rarbg.me:2710/announce&tr=udp://9.rarbg.com:2710/announce&tr=udp://9.rarbg.to:2710/announce&tr=udp://10.rarbg.me:80/announce&tr=udp://12.rarbg.me:80/announce&tr=udp://tracker.zond.org:80/announce&tr=udp://tracker.ilibr.org:6969/announce&tr=http://announce.torrentsmd.com:6969/announce&tr=udp://fr33domtracker.h33t.com:3310/announce$$lsname=Flatiners.2017.720p</link>
    <link>plugin://plugin.video.quasar/play?uri=magnet:?xt=urn:btih:4f66f708eaf28d4fd164343de309f6c01fa9bcc6&dn=Flatiners.2017.1080p&tr=udp://tracker.coppersurfer.tk:6969&tr=udp://coppersurfer.tk:6969/announce&tr=udp://tracker4.piratux.com:6969/announce&tr=udp://eddie4.nl:6969/announce&tr=udp://tracker.opentrackr.org:1337/announce&tr=udp://tracker.coppersurfer.tk:80&tr=udp://tracker.openbittorrent.com:80/announce&tr=udp://open.demonii.com:1337/announce&tr=udp://tracker.pomf.se&tr=udp://tracker.blackunicorn.xyz:6969&tr=udp://tracker.leechers-paradise.org:6969&tr=http://retracker.uln-ix.ru/announce&tr=http://tracker1.infohash.org/announce&tr=udp://p4p.arenabg.ch:1337&tr=udp://p4p.arenabg.com:1337&tr=udp://glotorrents.pw:6969/announce&tr=http://tracker.nwps.ws:6969/announce&tr=http://tracker.dler.org:6969/announce&tr=http://tracker.flashtorrents.org:6969/announce&tr=http://mgtracker.org:2710/announce&tr=http://retracker.adminko.org/announce&tr=http://torrent.fedoraproject.org:6969/announce&tr=http://tracker.best-torrents.net:6969/announce&tr=http://tracker.tfile.me/announce&tr=udp://exodus.desync.com:6969&tr=udp://torrent.gresille.org:80/announce&tr=http://tracker.aletorrenty.pl:2710/announce&tr=http://tracker.pubt.net:2710/announce&tr=http://exodus.desync.com/announce&tr=udp://tracker.publichd.eu:80/announce&tr=http://inferno.demonoid.ph:3389/announce&tr=udp://tracker.publicbt.com:80/announce&tr=http://tracker.ex.ua/announce&tr=udp://exodus.desync.com:6969&tr=http://exodus.desync.com/announce&tr=udp://tracker.istole.it:80/announce&tr=udp://tracker.1337x.org:80/announce&tr=http://fr33dom.h33t.com:3310/announce&tr=udp://tracker.1337x.org:80/announce&tr=http://tracker.torrentbay.to:6969/announce&tr=udp://tracker.publichd.eu:80/announce&tr=http://tracker.trackerfix.com/announce&tr=udp://tracker.ccc.de:80/announce&tr=udp://pow7.com:80/announce&tr=udp://tracker.token.ro:80/announce&tr=udp://ipv4.tracker.harry.lu:80/announce&tr=http://bt.rghost.net/announce&tr=http://cpleft.com:2710/announce&tr=udp://9.rarbg.me:2710/announce&tr=udp://9.rarbg.com:2710/announce&tr=udp://9.rarbg.to:2710/announce&tr=udp://10.rarbg.me:80/announce&tr=udp://12.rarbg.me:80/announce&tr=udp://tracker.zond.org:80/announce&tr=udp://tracker.ilibr.org:6969/announce&tr=http://announce.torrentsmd.com:6969/announce&tr=udp://fr33domtracker.h33t.com:3310/announce$$lsname=Flatiners.2017.1080p</link>
  </multilink>
</item>
<item>
  <title>L experience interdite (2017) torrent VO/VOSTFR</title>
  <thumbnail>https://images-na.ssl-images-amazon.com/images/M/MV5BMTExMTk2ODk0NDNeQTJeQWpwZ15BbWU4MDMxNTExNjIy._V1_UX182_CR0,0,182,268_AL_.jpg</thumbnail>
  <multilink>
    <link>plugin://plugin.video.quasar/play?uri=magnet:?xt=urn:btih:5a829c2cc829d1a3ecde19728eb3eadfbbfe5fef&dn=Flatliners.2017.720p.BluRay.x264-GECKOS&tr=http%3A%2F%2Ftracker.trackerfix.com%3A80%2Fannounce&tr=udp%3A%2F%2F9.rarbg.me%3A2710&tr=udp%3A%2F%2F9.rarbg.to%3A2710$$lsname=Flatliners.2017.720p.BluRay.x264-GECKOS</link>
    <link>plugin://plugin.video.quasar/play?uri=magnet:?xt=urn:btih:481918ca97fff81ae9490d99bdcfa4c7589abe83&dn=Flatliners.2017.1080p.BluRay.x264-GECKOS&tr=http%3A%2F%2Ftracker.trackerfix.com%3A80%2Fannounce&tr=udp%3A%2F%2F9.rarbg.me%3A2710&tr=udp%3A%2F%2F9.rarbg.to%3A2710$$lsname=Flatliners.2017.1080p.BluRay.x264-GECKOS</link>
  </multilink>
</item>
